hydrobricks/__init__.py
hydrobricks/_constants.py
hydrobricks/_hydrobricks.cp313-win_amd64.pyd
hydrobricks/_optional.py
hydrobricks/catchment.py
hydrobricks/forcing.py
hydrobricks/hdf5.dll
hydrobricks/hdf5_hl.dll
hydrobricks/hydro_units.py
hydrobricks/libcurl.dll
hydrobricks/netcdf.dll
hydrobricks/observations.py
hydrobricks/parameters.py
hydrobricks/results.py
hydrobricks/time_series.py
hydrobricks/trainer.py
hydrobricks/units.py
hydrobricks/utils.py
hydrobricks/zlib1.dll
hydrobricks/actions/__init__.py
hydrobricks/actions/action.py
hydrobricks/actions/action_glacier_evolution_area_scaling.py
hydrobricks/actions/action_glacier_evolution_delta_h.py
hydrobricks/actions/action_glacier_snow_to_ice_transformation.py
hydrobricks/actions/action_land_cover_change.py
hydrobricks/models/__init__.py
hydrobricks/models/model.py
hydrobricks/models/model_settings.py
hydrobricks/models/socont.py
hydrobricks/plotting/__init__.py
hydrobricks/plotting/plot_results.py
hydrobricks/preprocessing/__init__.py
hydrobricks/preprocessing/catchment_connectivity.py
hydrobricks/preprocessing/catchment_discretization.py
hydrobricks/preprocessing/catchment_topography.py
hydrobricks/preprocessing/glacier_evolution_area_scaling.py
hydrobricks/preprocessing/glacier_evolution_delta_h.py
hydrobricks/preprocessing/potential_solar_radiation.py
hydrobricks-0.8.6.dist-info/licenses/LICENSE
hydrobricks-0.8.6.dist-info/METADATA
hydrobricks-0.8.6.dist-info/WHEEL
hydrobricks-0.8.6.dist-info/top_level.txt
hydrobricks-0.8.6.dist-info/RECORD
