Metadata-Version: 2.4
Name: hydrobricks
Version: 0.8.6
Summary: A modular hydrological modelling framework
Author-email: "Pascal Horton et al." <pascal.horton@unibe.ch>
Maintainer: Pascal Horton, Anne-Laure Argentin
License-Expression: MIT
Project-URL: Source Code, https://github.com/hydrobricks/hydrobricks
Project-URL: Bug Tracker, https://github.com/hydrobricks/hydrobricks/issues
Classifier: Programming Language :: C++
Classifier: Programming Language :: Python :: 3
Requires-Python: >=3.10
License-File: LICENSE
Requires-Dist: cftime
Requires-Dist: numpy
Requires-Dist: HydroErr
Requires-Dist: pandas
Requires-Dist: pyyaml
Requires-Dist: StrEnum
Requires-Dist: dask
Requires-Dist: dask-expr
Provides-Extra: test
Requires-Dist: pytest>=6.0; extra == "test"
Dynamic: license-file
